LICENSE
MANIFEST.in
README.rst
setup.cfg
setup.py
LINEViewer.egg-info/PKG-INFO
LINEViewer.egg-info/SOURCES.txt
LINEViewer.egg-info/dependency_links.txt
LINEViewer.egg-info/not-zip-safe
LINEViewer.egg-info/top_level.txt
lineviewer/Analysis.py
lineviewer/FileHandler.py
lineviewer/Interface.py
lineviewer/LINEViewer.py
lineviewer/PanelData.py
lineviewer/PanelSpecs.py
lineviewer/PanelVisualize.py
lineviewer/__init__.py
lineviewer/static/LINEViewer_logo.png
lineviewer/static/favicon_256.ico