Metadata-Version: 1.1
Name: LINEViewer
Version: 0.2.2
Summary: Python based EEG analysis tool for a rough data overview
Home-page: https://github.com/miykael/LINEViewer
Author: Michael Notter
Author-email: michaelnotter@hotmail.com
License: GNU GENERAL PUBLIC LICENSE
Download-URL: https://github.com/miykael/LINEViewer/releases/tag/0.2.02
Keywords: LINE,LINEViewer,EEG
Platform: UNKNOWN
Classifier: Development Status :: 4 - Beta
Classifier: Intended Audience :: Science/Research
Classifier: License :: OSI Approved :: GNU Affero General Public License v3
Classifier: Operating System :: Microsoft :: Windows
Classifier: Operating System :: OS Independent
Classifier: Operating System :: POSIX :: Linux
Classifier: Programming Language :: Python :: 2.7
Classifier: Topic :: Scientific/Engineering
